deepinv/__about__.py
deepinv/__init__.py
deepinv/datasets/__init__.py
deepinv/datasets/base.py
deepinv/datasets/bsds500.py
deepinv/datasets/cbsd68.py
deepinv/datasets/cmrxrecon.py
deepinv/datasets/datagenerator.py
deepinv/datasets/div2k.py
deepinv/datasets/fastmri.py
deepinv/datasets/flickr2k.py
deepinv/datasets/fmd.py
deepinv/datasets/kohler.py
deepinv/datasets/lidc_idri.py
deepinv/datasets/lsdir.py
deepinv/datasets/patch_dataset.py
deepinv/datasets/random_sampler.py
deepinv/datasets/satellite.py
deepinv/datasets/set14.py
deepinv/datasets/skmtea.py
deepinv/datasets/urban100.py
deepinv/datasets/utils.py
deepinv/loss/__init__.py
deepinv/loss/augmentation.py
deepinv/loss/ei.py
deepinv/loss/loss.py
deepinv/loss/mc.py
deepinv/loss/measplit.py
deepinv/loss/moi.py
deepinv/loss/r2r.py
deepinv/loss/regularisers.py
deepinv/loss/scheduler.py
deepinv/loss/score.py
deepinv/loss/sup.py
deepinv/loss/sure.py
deepinv/loss/tv.py
deepinv/loss/adversarial/__init__.py
deepinv/loss/adversarial/base.py
deepinv/loss/adversarial/consistency.py
deepinv/loss/adversarial/uair.py
deepinv/loss/metric/__init__.py
deepinv/loss/metric/distortion.py
deepinv/loss/metric/functional.py
deepinv/loss/metric/metric.py
deepinv/loss/metric/perceptual.py
deepinv/loss/mri/__init__.py
deepinv/loss/mri/measplit.py
deepinv/loss/mri/sure.py
deepinv/models/GSPnP.py
deepinv/models/PDNet.py
deepinv/models/__init__.py
deepinv/models/ae.py
deepinv/models/artifactremoval.py
deepinv/models/base.py
deepinv/models/bm3d.py
deepinv/models/client.py
deepinv/models/complex.py
deepinv/models/diffunet.py
deepinv/models/dip.py
deepinv/models/dncnn.py
deepinv/models/drunet.py
deepinv/models/dsccp.py
deepinv/models/dynamic.py
deepinv/models/epll.py
deepinv/models/equivariant.py
deepinv/models/gan.py
deepinv/models/guided_diffusion.py
deepinv/models/icnn.py
deepinv/models/kernel_network.py
deepinv/models/median.py
deepinv/models/modl.py
deepinv/models/multispectral.py
deepinv/models/ncsnpp.py
deepinv/models/poisson2sparse.py
deepinv-0.3.7.dist-info/licenses/LICENSE
deepinv-0.3.7.dist-info/METADATA
deepinv-0.3.7.dist-info/WHEEL
deepinv-0.3.7.dist-info/top_level.txt
deepinv-0.3.7.dist-info/RECORD
