Metadata-Version: 2.4
Name: deepinv
Version: 0.3.7
Summary: DeepInverse: a PyTorch library for imaging with deep learning
Author: DeepInverse maintainers (see https://github.com/deepinv/deepinv/blob/main/MAINTAINERS.md)
License-Expression: BSD-3-Clause
Project-URL: Homepage, https://deepinv.github.io/
Project-URL: Source, https://github.com/deepinv/deepinv
Project-URL: Tracker, https://github.com/deepinv/deepinv/issues
Platform: any
Classifier: Development Status :: 4 - Beta
Classifier: Intended Audience :: Developers
Classifier: Intended Audience :: Science/Research
Classifier: Operating System :: OS Independent
Classifier: Programming Language :: Python :: 3
Classifier: Programming Language :: Python :: 3.10
Classifier: Programming Language :: Python :: 3.11
Classifier: Programming Language :: Python :: 3.12
Classifier: Topic :: Utilities
Classifier: Topic :: Scientific/Engineering
Classifier: Topic :: Software Development :: Libraries
Requires-Python: >=3.10
License-File: LICENSE
Requires-Dist: numpy
Requires-Dist: matplotlib
Requires-Dist: tqdm
Requires-Dist: torch>=2.2.0
Requires-Dist: torchvision
Requires-Dist: torchmetrics
Requires-Dist: einops
Requires-Dist: requests
Requires-Dist: h5py
Requires-Dist: natsort
Provides-Extra: test
Requires-Dist: pytest; extra == "test"
Requires-Dist: pytest-cov; extra == "test"
Requires-Dist: pytest-xdist; extra == "test"
Requires-Dist: coverage; extra == "test"
Requires-Dist: pytest-testmon; extra == "test"
Provides-Extra: doc
Requires-Dist: sphinx; extra == "doc"
Requires-Dist: sphinx_gallery; extra == "doc"
Requires-Dist: pydata_sphinx_theme; extra == "doc"
Requires-Dist: sphinxemoji; extra == "doc"
Requires-Dist: sphinx_copybutton; extra == "doc"
Requires-Dist: sphinx_autoapi; extra == "doc"
Requires-Dist: sphinx-design; extra == "doc"
Requires-Dist: sphinx_sitemap<2.7.0; extra == "doc"
Requires-Dist: sphinxcontrib.bibtex; extra == "doc"
Requires-Dist: nbformat; extra == "doc"
Provides-Extra: lint
Requires-Dist: black; extra == "lint"
Requires-Dist: ruff; extra == "lint"
Provides-Extra: denoisers
Requires-Dist: bm3d; extra == "denoisers"
Requires-Dist: bm4d<4.2.4; extra == "denoisers"
Requires-Dist: timm; extra == "denoisers"
Requires-Dist: PyWavelets; extra == "denoisers"
Requires-Dist: ptwt; extra == "denoisers"
Requires-Dist: FrEIA; extra == "denoisers"
Requires-Dist: pyiqa; extra == "denoisers"
Requires-Dist: kornia; extra == "denoisers"
Requires-Dist: torchkbnufft; extra == "denoisers"
Requires-Dist: libcpab; extra == "denoisers"
Requires-Dist: sigpy; extra == "denoisers"
Requires-Dist: astra-toolbox!=2.3.0,>=2.2.0; platform_system == "Linux" and extra == "denoisers"
Requires-Dist: spyrit>=3.0.0; platform_system == "Linux" and extra == "denoisers"
Requires-Dist: diffusers; extra == "denoisers"
Requires-Dist: transformers; extra == "denoisers"
Provides-Extra: dataset
Requires-Dist: datasets; extra == "dataset"
Requires-Dist: pandas; extra == "dataset"
Requires-Dist: pydicom; extra == "dataset"
Requires-Dist: mat73; extra == "dataset"
Requires-Dist: scipy; extra == "dataset"
Requires-Dist: nibabel; extra == "dataset"
Requires-Dist: rasterio; extra == "dataset"
Requires-Dist: blosc2; extra == "dataset"
Provides-Extra: training
Requires-Dist: wandb; extra == "training"
Requires-Dist: mlflow; extra == "training"
Dynamic: license-file
